rotalabs_graph/__init__.py
rotalabs_graph/_version.py
rotalabs_graph/analysis/__init__.py
rotalabs_graph/analysis/anomaly.py
rotalabs_graph/analysis/clusters.py
rotalabs_graph/analysis/metrics.py
rotalabs_graph/analysis/paths.py
rotalabs_graph/core/__init__.py
rotalabs_graph/core/config.py
rotalabs_graph/core/exceptions.py
rotalabs_graph/core/graph.py
rotalabs_graph/core/types.py
rotalabs_graph/integration/__init__.py
rotalabs_graph/propagation/__init__.py
rotalabs_graph/propagation/base.py
rotalabs_graph/propagation/eigentrust.py
rotalabs_graph/propagation/gnn.py
rotalabs_graph/propagation/pagerank.py
rotalabs_graph/propagation/weighted.py
rotalabs_graph/temporal/__init__.py
rotalabs_graph/temporal/decay.py
rotalabs_graph/temporal/dynamic.py
rotalabs_graph/temporal/history.py
rotalabs_graph/utils/__init__.py
rotalabs_graph/utils/helpers.py
rotalabs_graph/utils/serialization.py
rotalabs_graph-1.0.0.dist-info/METADATA
rotalabs_graph-1.0.0.dist-info/WHEEL
rotalabs_graph-1.0.0.dist-info/licenses/LICENSE
rotalabs_graph-1.0.0.dist-info/RECORD
