Metadata-Version: 2.4
Name: rotalabs-graph
Version: 1.0.0
Summary: GNN-based trust propagation for AI systems
Project-URL: Homepage, https://github.com/rotalabs/rotalabs-graph
Project-URL: Documentation, https://rotalabs.github.io/rotalabs-graph
Project-URL: Repository, https://github.com/rotalabs/rotalabs-graph
Project-URL: Issues, https://github.com/rotalabs/rotalabs-graph/issues
Author-email: Subhadip Mitra <subhadip@rotalabs.ai>, Rotalabs Research <research@rotalabs.ai>
License-Expression: AGPL-3.0-or-later
License-File: LICENSE
Keywords: ai-safety,gnn,graph,network-analysis,trust,trust-propagation
Classifier: Development Status :: 3 - Alpha
Classifier: Intended Audience :: Developers
Classifier: Intended Audience :: Science/Research
Classifier: License :: OSI Approved :: GNU Affero General Public License v3 or later (AGPLv3+)
Classifier: Operating System :: OS Independent
Classifier: Programming Language :: Python :: 3
Classifier: Programming Language :: Python :: 3.9
Classifier: Programming Language :: Python :: 3.10
Classifier: Programming Language :: Python :: 3.11
Classifier: Programming Language :: Python :: 3.12
Classifier: Topic :: Scientific/Engineering :: Artificial Intelligence
Classifier: Topic :: Security
Classifier: Typing :: Typed
Requires-Python: >=3.9
Requires-Dist: networkx>=3.0
Requires-Dist: pydantic>=2.0.0
Provides-Extra: all
Requires-Dist: matplotlib>=3.5; extra == 'all'
Requires-Dist: mkdocs-material>=9.0; extra == 'all'
Requires-Dist: mkdocs>=1.5; extra == 'all'
Requires-Dist: mkdocstrings[python]>=0.24; extra == 'all'
Requires-Dist: mypy>=1.0; extra == 'all'
Requires-Dist: plotly>=5.0; extra == 'all'
Requires-Dist: pytest-asyncio>=0.21; extra == 'all'
Requires-Dist: pytest-cov>=4.0; extra == 'all'
Requires-Dist: pytest>=7.0; extra == 'all'
Requires-Dist: ruff>=0.1.0; extra == 'all'
Requires-Dist: torch-geometric>=2.0; extra == 'all'
Requires-Dist: torch>=2.0; extra == 'all'
Provides-Extra: dev
Requires-Dist: mypy>=1.0; extra == 'dev'
Requires-Dist: pytest-asyncio>=0.21; extra == 'dev'
Requires-Dist: pytest-cov>=4.0; extra == 'dev'
Requires-Dist: pytest>=7.0; extra == 'dev'
Requires-Dist: ruff>=0.1.0; extra == 'dev'
Provides-Extra: docs
Requires-Dist: mkdocs-material>=9.0; extra == 'docs'
Requires-Dist: mkdocs>=1.5; extra == 'docs'
Requires-Dist: mkdocstrings[python]>=0.24; extra == 'docs'
Provides-Extra: gnn
Requires-Dist: torch-geometric>=2.0; extra == 'gnn'
Requires-Dist: torch>=2.0; extra == 'gnn'
Provides-Extra: viz
Requires-Dist: matplotlib>=3.5; extra == 'viz'
Requires-Dist: plotly>=5.0; extra == 'viz'
